{
  "5857829625": {
    "telegram_id": "5857829625",
    "telegram_username": "cektant96",
    "telegram_username_normalized": "cektant96",
    "telegram_name": "🟍",
    "nickname": "1n0k",
    "banned": false
  },
  "5848953120": {
    "telegram_id": "5848953120",
    "telegram_username": "",
    "telegram_username_normalized": "",
    "telegram_name": "ⵁ",
    "nickname": "kozavka333",
    "banned": false
  },
  "5162165364": {
    "telegram_id": "5162165364",
    "telegram_username": "kamysh_88",
    "telegram_username_normalized": "kamysh_88",
    "telegram_name": "Камыш🐢",
    "nickname": "Kuni_master",
    "banned": false
  },
  "5087423469": {
    "telegram_id": "5087423469",
    "telegram_username": "Systems_safety_small_use_wekrs",
    "telegram_username_normalized": "systems_safety_small_use_wekrs",
    "telegram_name": "Система безопасности малого пользования 𝚠𝚎𝚔𝚛𝚜🎄я солнышко (нет)",
    "nickname": "Wek3rsRTY",
    "banned": false
  },
  "6655980606": {
    "telegram_id": "6655980606",
    "telegram_username": "ttochkkame",
    "telegram_username_normalized": "ttochkkame",
    "telegram_name": "ᅠ🎀",
    "nickname": "WeinWaffel_",
    "banned": false
  },
  "6799441946": {
    "telegram_id": "6799441946",
    "telegram_username": "hermit7530",
    "telegram_username_normalized": "hermit7530",
    "telegram_name": "卄乇尺爪丨ㄒ",
    "nickname": "hermit7530",
    "banned": false
  },
  "2008792750": {
    "telegram_id": "2008792750",
    "telegram_username": "rain226",
    "telegram_username_normalized": "rain226",
    "telegram_name": "Despair",
    "nickname": "",
    "banned": false
  },
  "6464172897": {
    "telegram_id": "6464172897",
    "telegram_username": "ahmed28700",
    "telegram_username_normalized": "ahmed28700",
    "telegram_name": "Stairen",
    "nickname": "Stairen",
    "banned": false
  },
  "1903982852": {
    "telegram_id": "1903982852",
    "telegram_username": "qz_ah",
    "telegram_username_normalized": "qz_ah",
    "telegram_name": "quizix",
    "nickname": "",
    "banned": false
  },
  "7837079322": {
    "telegram_id": "7837079322",
    "telegram_username": "zmmxcmc",
    "telegram_username_normalized": "zmmxcmc",
    "telegram_name": "❀111",
    "nickname": "bebrina",
    "banned": false
  },
  "7742950680": {
    "telegram_id": "7742950680",
    "telegram_username": "Malborka",
    "telegram_username_normalized": "malborka",
    "telegram_name": "Грустик",
    "nickname": "",
    "banned": false
  },
  "1630065409": {
    "telegram_id": "1630065409",
    "telegram_username": "id00322",
    "telegram_username_normalized": "id00322",
    "telegram_name": "°",
    "nickname": "",
    "banned": false
  },
  "8600343380": {
    "telegram_id": "8600343380",
    "telegram_username": "",
    "telegram_username_normalized": "",
    "telegram_name": "имбецил",
    "nickname": "Srbi4an",
    "banned": false
  },
  "7753909753": {
    "telegram_id": "7753909753",
    "telegram_username": "",
    "telegram_username_normalized": "",
    "telegram_name": "Евгений",
    "nickname": "Unichtojitel",
    "banned": false
  },
  "7417865340": {
    "telegram_id": "7417865340",
    "telegram_username": "drakoshaminishapka",
    "telegram_username_normalized": "drakoshaminishapka",
    "telegram_name": "ᅠ",
    "nickname": "",
    "banned": false
  },
  "7136889655": {
    "telegram_id": "7136889655",
    "telegram_username": "warhamer4Ok",
    "telegram_username_normalized": "warhamer4ok",
    "telegram_name": "ㅤㅤㅤㅤ",
    "nickname": "",
    "banned": false
  },
  "7731048539": {
    "telegram_id": "7731048539",
    "telegram_username": "yaasnui",
    "telegram_username_normalized": "yaasnui",
    "telegram_name": "111",
    "nickname": "",
    "banned": false
  },
  "6239030851": {
    "telegram_id": "6239030851",
    "telegram_username": "ScYjvRsPmK",
    "telegram_username_normalized": "scyjvrspmk",
    "telegram_name": "_9Wprizrak5_",
    "nickname": "",
    "banned": false
  },
  "7255274196": {
    "telegram_id": "7255274196",
    "telegram_username": "Clintt3090",
    "telegram_username_normalized": "clintt3090",
    "telegram_name": "Игорь",
    "nickname": "",
    "banned": false
  }
}
